<?xml version='1.0' encoding='UTF-8'?>
<!-- Generated by LavishSettings v2 -->
<InnerSpaceSettings>
<Setting Name="Alleviation VI (Expert)">1</Setting>
<Setting Name="Fanaticism III (Expert)">1</Setting>
<Setting Name="Inquisition (Expert)">1</Setting>
<Setting Name="Redemption IV (Expert)">1</Setting>
<Setting Name="Ministration IX (Expert)">1</Setting>
<Setting Name="Smite Corruption IV (Expert)">1</Setting>
<Setting Name="Vengeance V (Expert)">1</Setting>
<Setting Name="Fanatic's Faith VI (Expert)">1</Setting>
<Setting Name="Heresy III (Expert)">1</Setting>
<Setting Name="Invocation VIII (Expert)">1</Setting>
<Setting Name="Tenacity VII (Expert)">1</Setting>
<Setting Name="Fanatical Healing VIII (Expert)">1</Setting>
<Setting Name="Inquest IV (Expert)">1</Setting>
<Setting Name="Repentance VI (Expert)">1</Setting>
<Setting Name="Fervent Faith III (Expert)">1</Setting>
<Setting Name="Litany V (Expert)">1</Setting>
<Setting Name="Sacred Armor VII (Expert)">1</Setting>
<Setting Name="Act of War V (Expert)">1</Setting>
<Setting Name="Tormenting Conversion IV (Expert)">1</Setting>
<Setting Name="Deny VII (Expert)">1</Setting>
<Setting Name="Dogma III (Expert)">1</Setting>
<Setting Name="Forced Obedience VI (Expert)">1</Setting>
<Setting Name="Condemn VIII (Expert)">1</Setting>
<Setting Name="Incarcerate V (Expert)">1</Setting>
<Setting Name="Purifying Flames VI (Expert)">1</Setting>
<Setting Name="Penance VIII (Expert)">1</Setting>
<Setting Name="Torment VIII (Expert)">1</Setting>
<Setting Name="Disorientation VII (Expert)">1</Setting>
<Setting Name="Heretic's Doom VI (Expert)">1</Setting>
<Setting Name="Malevolent Diatribe VII (Expert)">1</Setting>
</InnerSpaceSettings>
