<?xml version='1.0' encoding='UTF-8'?>
<!-- Generated by LavishSettings v2 -->
<InnerSpaceSettings>
<Setting Name="Ancestral Savior IV (Expert)">1</Setting>
<Setting Name="Ancestral Sentry (Expert)">1</Setting>
<Setting Name="Oberon III (Expert)">1</Setting>
<Setting Name="Transcendence VI (Expert)">1</Setting>
<Setting Name="Prophetic Ward V (Expert)">1</Setting>
<Setting Name="Rejuvenation IX (Expert)">1</Setting>
<Setting Name="Ancestral Mettle VI (Expert)">1</Setting>
<Setting Name="Premonition VII (Expert)">1</Setting>
<Setting Name="Torpor III (Expert)">1</Setting>
<Setting Name="Velium Winds VIII (Expert)">1</Setting>
<Setting Name="Lunar Attendant IV (Expert)">1</Setting>
<Setting Name="Ritual Healing VIII (Expert)">1</Setting>
<Setting Name="Spirit of the Mammoth VI (Expert)">1</Setting>
<Setting Name="Runic Armor VII (Expert)">1</Setting>
<Setting Name="Slothful Spirit III (Expert)">1</Setting>
<Setting Name="Wrath of the Ancients V (Expert)">1</Setting>
<Setting Name="Ancestral Avatar IV (Expert)">1</Setting>
<Setting Name="Ancestral Balm III (Expert)">1</Setting>
<Setting Name="Deteriorate VII (Expert)">1</Setting>
<Setting Name="Ursine Avatar VI (Expert)">1</Setting>
<Setting Name="Glacial Flames VI (Expert)">1</Setting>
<Setting Name="Ancestral Ward VIII (Expert)">1</Setting>
<Setting Name="Plague VIII (Expert)">1</Setting>
<Setting Name="Echoes of the Ancients VI (Expert)">1</Setting>
<Setting Name="Spirits VII (Expert)">1</Setting>
<Setting Name="Umbral Warding VII (Expert)">1</Setting>
</InnerSpaceSettings>
